centralcli/__init__.py
centralcli/boilerplate/README.md
centralcli/boilerplate/_cnx_allcalls.py
centralcli/boilerplate/allcalls.py
centralcli/caas.py
centralcli/cache.py
centralcli/classic/api/__init__.py
centralcli/classic/api/aiops.py
centralcli/classic/api/central.py
centralcli/classic/api/cloudauth.py
centralcli/classic/api/configuration.py
centralcli/classic/api/device_management.py
centralcli/classic/api/firmware.py
centralcli/classic/api/guest.py
centralcli/classic/api/kms.py
centralcli/classic/api/monitoring.py
centralcli/classic/api/other.py
centralcli/classic/api/platform.py
centralcli/classic/api/rapids.py
centralcli/classic/api/routing.py
centralcli/classic/api/topology.py
centralcli/classic/api/troubleshooting.py
centralcli/classic/api/visualrf.py
centralcli/cleaner.py
centralcli/cli.py
centralcli/clicommon.py
centralcli/client.py
centralcli/clioptions.py
centralcli/clitree/add.py
centralcli/clitree/assign.py
centralcli/clitree/batch/__init__.py
centralcli/clitree/batch/add.py
centralcli/clitree/batch/assign.py
centralcli/clitree/batch/batch.py
centralcli/clitree/batch/delete.py
centralcli/clitree/batch/update.py
centralcli/clitree/caas.py
centralcli/clitree/cancel.py
centralcli/clitree/check.py
centralcli/clitree/clone.py
centralcli/clitree/convert.py
centralcli/clitree/delete/delete.py
centralcli/clitree/delete/firmware.py
centralcli/clitree/dev.py
centralcli/clitree/export.py
centralcli/clitree/generate.py
centralcli/clitree/kick.py
centralcli/clitree/refresh.py
centralcli/clitree/rename.py
centralcli/clitree/set/firmware.py
centralcli/clitree/set/set.py
centralcli/clitree/show/audit.py
centralcli/clitree/show/bandwidth.py
centralcli/clitree/show/branch.py
centralcli/clitree/show/cloudauth.py
centralcli/clitree/show/firmware.py
centralcli/clitree/show/mpsk.py
centralcli/clitree/show/ospf.py
centralcli/clitree/show/overlay.py
centralcli/clitree/show/show.py
centralcli/clitree/show/ts.py
centralcli/clitree/show/wids.py
centralcli/clitree/test.py
centralcli-9.2.3.dist-info/METADATA
centralcli-9.2.3.dist-info/WHEEL
centralcli-9.2.3.dist-info/entry_points.txt
centralcli-9.2.3.dist-info/licenses/LICENSE
centralcli-9.2.3.dist-info/RECORD
