Metadata-Version: 2.4
Name: centralcli
Version: 9.2.3
Summary: A CLI for interacting with Aruba Central (Cloud Management Platform).  Facilitates bulk imports, exports, reporting.  A handy tool if you have devices managed by Aruba Central.
License-Expression: MIT
License-File: LICENSE
Keywords: cli,Aruba,Aruba Networks,Aruba Central,HPE,HPE Networking,API,RESTFUL,REST
Author: Wade Wells (Pack3tL0ss)
Author-email: cencli@consolepi.com
Maintainer: Wade Wells (Pack3tL0ss)
Maintainer-email: cencli@consolepi.com
Requires-Python: >=3.10,<4.0
Classifier: Development Status :: 5 - Production/Stable
Classifier: Environment :: Console
Classifier: Programming Language :: Python :: 3.10
Classifier: Programming Language :: Python :: 3.11
Classifier: Programming Language :: Python :: 3.12
Classifier: Programming Language :: Python :: 3.13
Classifier: Programming Language :: Python :: 3.14
Classifier: Programming Language :: Python :: 3.13
Classifier: Programming Language :: Python :: 3.14
Classifier: License :: OSI Approved :: MIT License
Provides-Extra: hook-proxy
Provides-Extra: speedups
Provides-Extra: xlsx
Requires-Dist: Brotli ; (platform_python_implementation == "CPython") and (extra == "speedups")
Requires-Dist: PyYAML (>=6)
Requires-Dist: aiodns (>=3.2.0) ; (platform_system != "Windows") and (extra == "speedups")
Requires-Dist: aiohttp (>=3)
Requires-Dist: asyncio (>=3)
Requires-Dist: brotlicffi ; (platform_python_implementation != "CPython") and (extra == "speedups")
Requires-Dist: click (<=7.1.2)
Requires-Dist: colorama ; platform_system == "Windows"
Requires-Dist: eval_type_backport ; python_version < "3.10"
Requires-Dist: fastapi ; extra == "hook-proxy"
Requires-Dist: fuzzywuzzy
Requires-Dist: ipaddress
Requires-Dist: jinja2
Requires-Dist: levenshtein
Requires-Dist: oauthlib (>=3.2.2)
Requires-Dist: pendulum (>=2)
Requires-Dist: protobuf
Requires-Dist: psutil ; extra == "hook-proxy"
Requires-Dist: pycares (<5.0.0) ; (platform_system != "Windows") and (extra == "speedups")
Requires-Dist: pycentral (>=0.0.3)
Requires-Dist: pydantic (>=2.0.0)
Requires-Dist: pylibyaml (>=0.1.0)
Requires-Dist: requests_oauthlib (>=2.0.0)
Requires-Dist: rich (>=10)
Requires-Dist: shellingham (>=1)
Requires-Dist: stringenum ; python_version < "3.11"
Requires-Dist: tablib (>=3)
Requires-Dist: tablib[xlsx] ; extra == "xlsx"
Requires-Dist: tabulate (>=0.8)
Requires-Dist: tinydb (>=4)
Requires-Dist: typer (>=0.6,<0.11.0)
Requires-Dist: uniplot (>=0.13.0)
Requires-Dist: uvicorn ; extra == "hook-proxy"
Project-URL: Documentation, https://central-api-cli.readthedocs.org
Project-URL: Repository, https://github.com/Pack3tL0ss/central-api-cli
Project-URL: issues, https://github.com/Pack3tL0ss/central-api-cli/issues
